sortbybytes/__init__.py
sortbybytes/formatter.py
sortbybytes/sorter.py
sortbybytes-0.1.3.dist-info/licenses/LICENSE
sortbybytes-0.1.3.dist-info/METADATA
sortbybytes-0.1.3.dist-info/WHEEL
sortbybytes-0.1.3.dist-info/top_level.txt
sortbybytes-0.1.3.dist-info/RECORD
