Metadata-Version: 2.4
Name: sortbybytes
Version: 0.1.3
Summary: Format and sort byte values like 25.6MB, 5.6KB
Author-email: Praveenkumar Nedumaran <creatorpravin@mail.com>
License-Expression: MIT
Requires-Python: >=3.7
License-File: LICENSE
Dynamic: license-file
